pysparkextra/__init__.py
pysparkextra/__pkginfo__.py
pysparkextra/arrows.py
pysparkextra/funcs.py
pysparkextra/metrics.py
pysparkextra/unittestcase.py
pysparkextra/util.py
tests/__init__.py
tests/test_arrows.py
tests/test_spark_arrows.py
tests/test_spark_funcs.py
tests/test_spark_metrics.py
tests/test_util.py
pysparkextra-0.4.2.dist-info/METADATA
pysparkextra-0.4.2.dist-info/WHEEL
pysparkextra-0.4.2.dist-info/top_level.txt
pysparkextra-0.4.2.dist-info/RECORD
