Metadata-Version: 2.1
Name: pysparkextra
Version: 0.4.2
Summary: extra utilities for pyspark.sql
Home-page: https://github.com/scravy/pysparkextra
Author: Julian Fleischer
Author-email: tirednesscankill@warhog.net
License: UNKNOWN
Platform: UNKNOWN
Classifier: Programming Language :: Python :: 3
Classifier: License :: OSI Approved :: MIT License
Classifier: Operating System :: OS Independent
Requires-Python: >=3.8
Requires-Dist: pyspark (>=3.0.0)
